keel/__init__.py
keel/keel.py
keel/mode.py
keel/ui.py
keel/util_logger.py
keel/util_ps.py
keel-0.1.dist-info/METADATA
keel-0.1.dist-info/RECORD
keel-0.1.dist-info/WHEEL
keel-0.1.dist-info/top_level.txt
