Metadata-Version: 2.1
Name: keel
Version: 0.1
Summary: Kill proccesses effectively and easily
Home-page: https://github.com/modelorona/keel
Author: Anguel Hristozov
Author-email: angel.hristozov@gmail.com
License: UNKNOWN
Platform: UNKNOWN
Classifier: Programming Language :: Python :: 3
Classifier: License :: OSI Approved :: MIT License
Classifier: Operating System :: OS Independent
Classifier: Environment :: Console :: Curses
Classifier: Natural Language :: English
